aiomcrcon/__init__.py
aiomcrcon/client.py
py_aio_mcrcon-1.0.1.dist-info/METADATA
py_aio_mcrcon-1.0.1.dist-info/WHEEL
py_aio_mcrcon-1.0.1.dist-info/licenses/LICENSE
py_aio_mcrcon-1.0.1.dist-info/RECORD
