Metadata-Version: 2.1
Name: py-aio-mcrcon
Version: 1.0.1
Summary: An async Minecraft RCON client library with support for fragmented responses.
Project-URL: Source, https://github.com/arvitus/aiomcrcon
Project-URL: Issues, https://github.com/arvitus/aiomcrcon/issues
Author: 3D_MAMA
License-File: LICENSE
Classifier: License :: OSI Approved :: GNU General Public License v3 (GPLv3)
Classifier: Operating System :: OS Independent
Classifier: Programming Language :: Python :: 3
Requires-Python: >=3.9
